Metadata-Version: 2.4
Name: prefect-client
Version: 3.6.15
Summary: Workflow orchestration and management.
Project-URL: Changelog, https://github.com/PrefectHQ/prefect/releases
Project-URL: Documentation, https://docs.prefect.io
Project-URL: Source, https://github.com/PrefectHQ/prefect
Project-URL: Tracker, https://github.com/PrefectHQ/prefect/issues
Author-email: "Prefect Technologies, Inc." <help@prefect.io>
License: Apache-2.0
License-File: LICENSE
Classifier: Intended Audience :: Developers
Classifier: Intended Audience :: System Administrators
Classifier: License :: OSI Approved :: Apache Software License
Classifier: Natural Language :: English
Classifier: Programming Language :: Python :: 3 :: Only
Classifier: Programming Language :: Python :: 3.10
Classifier: Programming Language :: Python :: 3.11
Classifier: Programming Language :: Python :: 3.12
Classifier: Programming Language :: Python :: 3.13
Classifier: Programming Language :: Python :: 3.14
Classifier: Topic :: Software Development :: Libraries
Requires-Python: <3.15,>=3.10
Requires-Dist: anyio<5.0.0,>=4.4.0
Requires-Dist: asgi-lifespan<3.0,>=1.0
Requires-Dist: cachetools<7.0,>=5.3
Requires-Dist: cloudpickle<4.0,>=2.0
Requires-Dist: coolname<4.0.0,>=1.0.4
Requires-Dist: dateparser<2.0.0,>=1.1.1
Requires-Dist: exceptiongroup>=1.0.0
Requires-Dist: fastapi<1.0.0,>=0.111.0
Requires-Dist: fsspec>=2022.5.0
Requires-Dist: graphviz>=0.20.1
Requires-Dist: griffe<2.0.0,>=0.49.0
Requires-Dist: httpcore<2.0.0,>=1.0.5
Requires-Dist: httpx[http2]!=0.23.2,>=0.23
Requires-Dist: humanize<5.0.0,>=4.9.0
Requires-Dist: jsonpatch<2.0,>=1.32
Requires-Dist: jsonschema<5.0.0,>=4.18.0
Requires-Dist: opentelemetry-api<2.0.0,>=1.27.0
Requires-Dist: orjson<4.0,>=3.7
Requires-Dist: packaging<25.1,>=21.3
Requires-Dist: pathspec>=0.8.0
Requires-Dist: pendulum<4,>=3.0.0; python_version < '3.13'
Requires-Dist: prometheus-client>=0.20.0
Requires-Dist: pydantic!=2.11.0,!=2.11.1,!=2.11.2,!=2.11.3,!=2.11.4,<3.0.0,>=2.10.1
Requires-Dist: pydantic-core<3.0.0,>=2.12.0
Requires-Dist: pydantic-extra-types<3.0.0,>=2.8.2
Requires-Dist: pydantic-settings!=2.9.0,<3.0.0,>2.2.1
Requires-Dist: python-dateutil<3.0.0,>=2.8.2
Requires-Dist: python-slugify<9.0,>=5.0
Requires-Dist: pytz<2026,>=2021.1
Requires-Dist: pyyaml<7.0.0,>=5.4.1
Requires-Dist: rfc3339-validator<0.2.0,>=0.1.4
Requires-Dist: rich<15.0,>=11.0
Requires-Dist: ruamel-yaml-clib>=0.2.8; platform_python_implementation == 'CPython'
Requires-Dist: ruamel-yaml>=0.17.0
Requires-Dist: sniffio<2.0.0,>=1.3.0
Requires-Dist: toml>=0.10.0
Requires-Dist: typing-extensions<5.0.0,>=4.10.0
Requires-Dist: uvicorn!=0.29.0,>=0.14.0
Requires-Dist: websockets<17.0,>=15.0.1
Requires-Dist: whenever<0.10.0,>=0.7.3; python_version >= '3.13'
Provides-Extra: notifications
Requires-Dist: apprise<2.0.0,>=1.1.0; extra == 'notifications'
